pyundergraduate/Differentiation.py
pyundergraduate/Integration.py
pyundergraduate/Interpolation.py
pyundergraduate/ODE_Solvers.py
pyundergraduate/RootFinder.py
pyundergraduate/__init__.py
pyundergraduate-0.0.3.dist-info/LICENSE
pyundergraduate-0.0.3.dist-info/METADATA
pyundergraduate-0.0.3.dist-info/WHEEL
pyundergraduate-0.0.3.dist-info/top_level.txt
pyundergraduate-0.0.3.dist-info/RECORD
