Metadata-Version: 2.1
Name: pyundergraduate
Version: 0.0.3
Summary: A package for numerical analysis with python
Home-page: https://github.com/ScientificArchisman/pyundergraduate
Author: Archisman Chakraborti
Author-email: archismanninja@gmail.com
License: MIT
Keywords: python,scince,numerical analysis,physics
Platform: UNKNOWN
Classifier: Development Status :: 1 - Planning
Classifier: Intended Audience :: Education
Classifier: Programming Language :: Python :: 3
Classifier: Operating System :: Unix
Classifier: Operating System :: MacOS :: MacOS X
Classifier: Operating System :: Microsoft :: Windows
License-File: LICENSE
Requires-Dist: numpy
Requires-Dist: scipy
Requires-Dist: matplotlib
Requires-Dist: jupyter
Requires-Dist: scienceplots
